simple_django_tequila/__init__.py
simple_django_tequila/tequila.py
simple_django_tequila-2.0.2.dist-info/DESCRIPTION.rst
simple_django_tequila-2.0.2.dist-info/METADATA
simple_django_tequila-2.0.2.dist-info/RECORD
simple_django_tequila-2.0.2.dist-info/WHEEL
simple_django_tequila-2.0.2.dist-info/metadata.json
simple_django_tequila-2.0.2.dist-info/top_level.txt
