Metadata-Version: 2.0
Name: simple-django-tequila
Version: 2.0.2
Summary: Simple django login backend for tequila
Home-page: https://github.com/the-glu/django-tequila
Author: Maximilien Cuony
Author-email: simple_django_tequila@fioupfioup.ch
License: UNKNOWN
Platform: UNKNOWN
Classifier: Programming Language :: Python
Classifier: Development Status :: 5 - Production/Stable
Classifier: License :: OSI Approved :: BSD License
Classifier: Operating System :: OS Independent
Classifier: Programming Language :: Python :: 2.7
Classifier: Programming Language :: Python :: 3
Classifier: Topic :: Software Development :: Libraries
Requires-Dist: requests
